{
    "name": "Convert Audio",
    "revision": 3,
    "minimumVersion": "1.0.0.0",
    "description": "Will convert audio files to the specified format and replace the original file.",
    "group": "Audio",
    "save": true,
    "parts": [
        {
            "node": "FileFlows.AudioNodes.AudioFile",
            "uid": "00000000-0000-0000-0000-000000000001",
            "xPos": 370,
            "yPos": 50,
            "connections": [
                {
                    "input": 1,
                    "output": 1,
                    "node": "00000000-0000-0000-0000-000000000002"
                }
            ]
        },
        {
            "node": "FileFlows.AudioNodes.ConvertAudio",
            "uid": "00000000-0000-0000-0000-000000000002",
            "xPos": 370,
            "yPos": 220,
            "outputs": 2,
            "model": {
                "SkipIfCodecMatches": true
            }
        },
        {
            "node": "FileFlows.BasicNodes.File.ReplaceOriginal",
            "uid": "00000000-0000-0000-0000-000000000003",
            "xPos": 370,
            "yPos": 390
        },
        {
            "node": "FileFlows.BasicNodes.File.MoveFile",
            "uid": "00000000-0000-0000-0000-000000000004",
            "xPos": 370,
            "yPos": 390,
            "model": {
                "MoveFolder": true,
                "DeleteOriginal": false,
                "DestinationPath": "/media"
            }
        },
        {
            "node": "FileFlows.BasicNodes.File.DeleteSourceDirectory",
            "Name": "Delete Source Folder If Empty",
            "uid": "00000000-0000-0000-0000-000000000005",            
            "xPos": 370,
            "yPos": 560,
            "model": {
                "IfEmpty": true,
                "IncludePatterns": [
                    "mp3",
                    "aac",
                    "ogg",
                    "flac",
                    "wav",
                    "m4a"
                ]
            }
        }
    ],
    "fields": [
        {
            "uid": "00000000-0000-0000-0000-000000000002",
            "type": "Select",
            "name": "Codec",
            "label": "Audio Codec",
            "help": "The audio codec to use for encoding",
            "parameters": {
                "options": [
                    {
                        "label": "AAC",
                        "value": "aac"
                    },
                    {
                        "label": "MP3",
                        "value": "mp3"
                    },
                    {
                        "label": "OGG",
                        "value": "ogg"
                    },
                    {
                        "label": "WAV",
                        "value": "wav"
                    }
                ]
            }
        },
        {
            "uid": "00000000-0000-0000-0000-000000000002",
            "type": "Select",
            "name": "Bitrate",
            "label": "Bitrate",
            "help": "The bitrate for the audio file",
            "parameters": {
                "options": [
                    {
                        "label": "64 Kbps",
                        "value": 64
                    },
                    {
                        "label": "96 Kbps",
                        "value": 96
                    },
                    {
                        "label": "128 Kbps",
                        "value": 128
                    },
                    {
                        "label": "160 Kbps",
                        "value": 160
                    },
                    {
                        "label": "192 Kbps",
                        "value": 192
                    },
                    {
                        "label": "224 Kbps",
                        "value": 224
                    },
                    {
                        "label": "256 Kbps",
                        "value": 256
                    },
                    {
                        "label": "288 Kbps",
                        "value": 288
                    },
                    {
                        "label": "320 Kbps",
                        "value": 320
                    }
                ]
            }
        },
        {
          "uid": "00000000-0000-0000-0000-000000000002",
          "type": "Select",
          "name": "Output-1",
          "label": "Output File",
          "help": "Where the newly converted file should be saved to",
          "parameters": {
            "options": [
              {
                "label": "Replace Original File",
                "value": "00000000-0000-0000-0000-000000000003"
              },
              {
                "label": "Save to Folder",
                "value": "00000000-0000-0000-0000-000000000004"
              }
            ]
          }
        },
        {
          "uid": "00000000-0000-0000-0000-000000000004",
          "type": "Directory",
          "required": true,
          "label": "Destination",
          "help": "The destination directory where the file should be save to",
          "name": "DestinationPath",
          "default": "/media",
          "conditions": [
            {
              "Property": "Output File",
              "Value": "00000000-0000-0000-0000-000000000004"
            }
          ]
        },
        {
          "uid": "00000000-0000-0000-0000-000000000004",
          "type": "Switch",
          "name": "DeleteOriginal",
          "default": false,
          "label": "Delete Original File",
          "help": "If the original file should be deleted after converting",
          "conditions": [
            {
              "Property": "Output File",
              "Value": "00000000-0000-0000-0000-000000000004"
            }
          ]
        },
        {
          "uid": "00000000-0000-0000-0000-000000000004",
          "type": "Switch",
          "name": "Output-1",
          "default": false,
          "label": "Delete Original Folder If Empty",
          "help": "If the original folder should be deleted if there are no more audio files found",
          "value": {
            "true": "00000000-0000-0000-0000-000000000005",
            "false": ""
          },
          "conditions": [
            {
              "Property": "Output File",
              "Value": "00000000-0000-0000-0000-000000000004"
            },
            {
              "Property": "Delete Original File",
              "Value": true
            }
          ]
        }
    ]
}